testreqstatus/__init__.py
testreqstatus/requirement_test_results.py
testreqstatus/requirement_tests.py
testreqstatus-0.6.0.dist-info/METADATA
testreqstatus-0.6.0.dist-info/WHEEL
testreqstatus-0.6.0.dist-info/licenses/LICENSE.txt
testreqstatus-0.6.0.dist-info/RECORD
