Metadata-Version: 2.3
Name: testreqstatus
Version: 0.6.0
Summary: parse test results to inform requirements
Project-URL: Documentation, https://github.com/zacharyburnett/testreqstatus#readme
Project-URL: Issues, https://github.com/zacharyburnett/testreqstatus/issues
Project-URL: Source, https://github.com/zacharyburnett/testreqstatus
Author-email: zacharyburnett <zburnett@stsci.edu>
License:                     GNU GENERAL PUBLIC LICENSE
License-File: LICENSE.txt
Classifier: Programming Language :: Python
Classifier: Programming Language :: Python :: 3.10
Classifier: Programming Language :: Python :: 3.11
Classifier: Programming Language :: Python :: 3.12
Classifier: Programming Language :: Python :: Implementation :: CPython
Requires-Python: >=3.10
Requires-Dist: junitparser
Provides-Extra: test
Requires-Dist: pytest; extra == 'test'
